birdvoxdetect
