Metadata-Version: 2.1
Name: birdvoxdetect
Version: 0.2.0
Summary: Bioacoustic monitoring of nocturnal bird migration
Home-page: https://github.com/BirdVox/birdvoxdetect
Author: Vincent Lostanlen, Justin Salamon, Andrew Farnsworth, Steve Kelling, and Juan Pablo Bello
Author-email: vincent.lostanlen@nyu.edu
License: MIT
Project-URL: Source, https://github.com/BirdVox/birdvoxdetect
Project-URL: Tracker, https://github.com/BirdVox/birdvoxdetect/issues
Keywords: tfrecord
Platform: UNKNOWN
Classifier: Development Status :: 3 - Alpha
Classifier: License :: OSI Approved :: MIT License
Classifier: Topic :: Multimedia :: Sound/Audio :: Analysis
Classifier: Programming Language :: Python :: 3
Classifier: Programming Language :: Python :: 3.6
Provides-Extra: docs
Provides-Extra: tests
